PremiumCalculator/__init__.py
PremiumCalculator/dateTime.py
PremiumCalculator/featured1.py
PremiumCalculator/featured2.py
PremiumCalculator/featured3.py
PremiumCalculator/featured4.py
premiumcalculator-0.1.2.dist-info/licenses/LICENSE
premiumcalculator-0.1.2.dist-info/METADATA
premiumcalculator-0.1.2.dist-info/WHEEL
premiumcalculator-0.1.2.dist-info/top_level.txt
premiumcalculator-0.1.2.dist-info/RECORD
