Metadata-Version: 2.4
Name: PremiumCalculator
Version: 0.1.2
Summary: A simple calculator package
Home-page: https://github.com/almuksid/PremiumCalculator
Author: Al Muksid
Author-email: Al Muksid <programming.me01@gmail.com>
License: MIT
Project-URL: Homepage, https://github.com/almuksid/PremiumCalculator
Classifier: Programming Language :: Python :: 3
Classifier: License :: OSI Approved :: MIT License
Classifier: Operating System :: Microsoft :: Windows
Requires-Python: >=3.7
License-File: LICENSE
Dynamic: license-file
